pms/__init__.py
pms/_version.py
pms/cli.py
pms/py.typed
pms/sensor.py
pms/core/__init__.py
pms/core/reader.py
pms/core/sensor.py
pms/core/types.py
pms/extra/__init__.py
pms/extra/bridge.py
pms/extra/influxdb.py
pms/extra/mqtt.py
pms/sensors/__init__.py
pms/sensors/base.py
pms/sensors/bosch_sensortec/__init__.py
pms/sensors/bosch_sensortec/mcu680.py
pms/sensors/honeywell/__init__.py
pms/sensors/honeywell/extra_commands.py
pms/sensors/honeywell/hpma115c0.py
pms/sensors/honeywell/hpma115s0.py
pms/sensors/novafitness/__init__.py
pms/sensors/novafitness/extra_commands.py
pms/sensors/novafitness/sds01x.py
pms/sensors/novafitness/sds198.py
pms/sensors/plantower/__init__.py
pms/sensors/plantower/pms3003.py
pms/sensors/plantower/pms5003s.py
pms/sensors/plantower/pms5003st.py
pms/sensors/plantower/pms5003t.py
pms/sensors/plantower/pmsx003.py
pms/sensors/sensirion/__init__.py
pms/sensors/sensirion/sps30.py
pms/sensors/winsen/__init__.py
pms/sensors/winsen/mhz19b.py
pms/sensors/winsen/zh0xx.py
pypms-0.8.0.dist-info/METADATA
pypms-0.8.0.dist-info/WHEEL
pypms-0.8.0.dist-info/entry_points.txt
pypms-0.8.0.dist-info/licenses/LICENSE
pypms-0.8.0.dist-info/RECORD
