Metadata-Version: 2.4
Name: pypms
Version: 0.8.0
Summary: Data acquisition and logging for Air Quality Sensors with UART interface
Project-URL: Homepage, https://avaldebe.github.io/PyPMS
Project-URL: Repository, https://github.com/avaldebe/PyPMS
Author-email: Alvaro Valdebenito <avaldebe@gmail.com>
License-File: LICENSE
Keywords: air quality,particulate matter
Classifier: Development Status :: 4 - Beta
Classifier: Intended Audience :: Science/Research
Classifier: License :: OSI Approved :: MIT License
Classifier: Natural Language :: English
Classifier: Operating System :: OS Independent
Classifier: Programming Language :: Python :: 3 :: Only
Classifier: Programming Language :: Python :: 3.9
Classifier: Programming Language :: Python :: 3.10
Classifier: Programming Language :: Python :: 3.11
Classifier: Programming Language :: Python :: 3.12
Classifier: Programming Language :: Python :: 3.13
Classifier: Topic :: Scientific/Engineering :: Atmospheric Science
Classifier: Topic :: Terminals :: Serial
Classifier: Topic :: Utilities
Classifier: Typing :: Typed
Requires-Python: <4.0,>=3.9
Requires-Dist: importlib-metadata>=3.6; python_version < '3.10'
Requires-Dist: loguru>=0.7.0
Requires-Dist: pyserial>=3.5
Requires-Dist: typer-slim>=0.12.0
Provides-Extra: influxdb
Requires-Dist: influxdb>=5.2.0; extra == 'influxdb'
Provides-Extra: mqtt
Requires-Dist: paho-mqtt>=2.1.0; extra == 'mqtt'
